{
    "general": {
        "search_engine": "google",
        "results_cnt": 149000000,
        "search_time": 0.67,
        "language": "en",
        "mobile": false,
        "basic_view": false,
        "search_type": "text",
        "page_title": "Illinois storm article - Google Search",
        "code_version": "1.106",
        "timestamp": "2023-07-27T01:26:41.317Z"
    },
    "input": {
        "original_url": "http://www.google.com/search?q=Illinois+storm+article&start=15&lum_json=1",
        "user_agent": "Mozilla/5.0 (Macintosh; Intel Mac OS X 10_11_5) AppleWebKit/607.1.40 (KHTML, like Gecko) Version/12.1.2 Safari/607.1.40",
        "request_id": "hl_c3a9eb28_g5rmijicnq8"
    },
    "organic": [
        {
            "link": "https://www.isws.illinois.edu/pubdoc/iem/iswsiem2006-06.pdf",
            "display_link": "https://www.isws.illinois.edu \u203a iswsiem2006-06",
            "title": "Severe Storms in the Midwest",
            "description": "Champaign, IL. Illinois State Water Survey Report I/EM 2006-06 ... weather systems to warm-season precipitation in the U.S. Journal Applied Meteorology, 25:.",
            "extensions": [
                {
                    "inline": true,
                    "type": "text",
                    "text": "by SA Changnon",
                    "rank": 1
                },
                {
                    "inline": true,
                    "type": "text",
                    "text": "Cited by 28",
                    "rank": 2
                },
                {
                    "type": "text",
                    "text": "84 pages",
                    "rank": 3
                }
            ],
            "rank": 1,
            "global_rank": 1
        },
        {
            "link": "https://www.thecentersquare.com/illinois/article_29548878-16c1-11ee-913b-ef3ec1b9e7c3.html",
            "display_link": "https://www.thecentersquare.com \u203a illinois \u203a article_2954...",
            "title": "Illinois quick hits: Storms bring damage across state",
            "description": "Storms bring damage across state. ... FILE - Illinois storm damage ... Strong thunderstorms moved through Illinois Thursday, downing trees, ...",
            "extensions": [
                {
                    "inline": true,
                    "type": "text",
                    "text": "Jun 29, 2023",
                    "rank": 1
                }
            ],
            "rank": 2,
            "global_rank": 2
        },
        {
            "link": "https://abcnews.go.com/US/tornadoes-midwest-floods-northeast-heat-southwest/story?id=101204375",
            "display_link": "https://abcnews.go.com \u203a story",
            "title": "Fatality confirmed in Vermont flooding amid extreme weather ...",
            "description": "Storms spawned multiple twisters across northern Illinois on Wednesday evening that knocked down trees, ripped off roofs and disrupted hundreds ...",
            "extensions": [
                {
                    "inline": true,
                    "type": "text",
                    "text": "Jul 14, 2023",
                    "rank": 1
                }
            ],
            "rank": 3,
            "global_rank": 3
        },
        {
            "link": "https://twitter.com/IL_Storm_Chaser",
            "display_link": "https://twitter.com \u203a IL_Storm_Chaser",
            "title": "Illinois Storm Chasers (@IL_Storm_Chaser) / Twitter",
            "description": "A brief clip of a potential tornado/funnel in Naperville, IL earlier this ... We're working on our next article now and should have it out in the 4-5pm ...",
            "rank": 4,
            "global_rank": 4
        },
        {
            "link": "https://www.fox32chicago.com/news/weather-service-governor-to-survey-illinois-storm-damage",
            "display_link": "https://www.fox32chicago.com \u203a news \u203a weather-service...",
            "title": "Weather service, governor to survey Illinois storm damage",
            "description": "Weather service, governor to survey Illinois storm damage ... article. OTTAWA, Ill. (AP) - The National Weather Service says survey teams ...",
            "extensions": [
                {
                    "inline": true,
                    "type": "text",
                    "text": "Mar 1, 2017",
                    "rank": 1
                }
            ],
            "rank": 5,
            "global_rank": 5
        },
        {
            "link": "https://illinoisstormchasers.com/weather-information-2/",
            "display_link": "https://illinoisstormchasers.com \u203a weather-information-2",
            "title": "Weather Information - Illinois Storm Chasers, LLC.",
            "description": "(11:30AM Wed, July 26th 2023) Wednesday morning update on a few disturbances that will continue to move through the region through tonight, bringing the ...",
            "extensions": [
                {
                    "type": "missing",
                    "text": "article",
                    "rank": 1
                },
                {
                    "type": "must_include",
                    "text": "article",
                    "link": "https://www.google.com/search?gl=us&hl=en&q=Illinois+storm+%22article%22&sa=X&ved=2ahUKEwimpYvZ3a2AAxXNBIgKHQfFAwY4DxDm3gJ6BAgaEAE",
                    "rank": 2
                }
            ],
            "rank": 6,
            "global_rank": 6
        },
        {
            "link": "https://thesouthern.com/news/local/weather/weather-forecast-illinois-storms-severe-cold-front/article_6b9b7b48-ef1a-5850-80db-69317e08f792.html",
            "display_link": "https://thesouthern.com \u203a news \u203a local \u203a weather \u203a article...",
            "title": "Small chance of severe storms in Illinois Thursday",
            "description": "Showers and storms are in the forecast today, especially during the afternoon and evening with a cold front. Damaging wind, hail, and ...",
            "extensions": [
                {
                    "inline": true,
                    "type": "text",
                    "text": "7 days ago",
                    "rank": 1
                }
            ],
            "rank": 7,
            "global_rank": 7
        },
        {
            "link": "https://www.news-gazette.com/news/photo-gallery-storms-wallop-east-central-illinois/collection_33f2c821-cfa5-5730-aa58-cd3a58138e13.html",
            "display_link": "https://www.news-gazette.com \u203a news \u203a photo-gallery-st...",
            "title": "PHOTO GALLERY: Storms wallop East Central Illinois",
            "description": "Mature trees were split in two and shredded of limbs and leaves, semis were blown over on the interstate backing up traffic for hours, ...",
            "extensions": [
                {
                    "inline": true,
                    "type": "text",
                    "text": "Jun 29, 2023",
                    "rank": 1
                }
            ],
            "rank": 8,
            "global_rank": 8
        },
        {
            "link": "https://nypost.com/2023/07/01/severe-storms-threaten-july-4-weekend-plans/",
            "display_link": "https://nypost.com \u203a 2023/07/01 \u203a severe-storms-threa...",
            "title": "Severe storms threaten July 4 weekend plans",
            "description": "The Storm Prediction Center has highlighted eastern Missouri, Illinois, Indiana and western Kentucky for being in an enhanced risk for ...",
            "extensions": [
                {
                    "inline": true,
                    "type": "text",
                    "text": "Jul 1, 2023",
                    "rank": 1
                }
            ],
            "rank": 9,
            "global_rank": 9
        },
        {
            "link": "https://weather.com/news/news/2023-03-31-tornadoes-storms-arkansas-tennessee-illinois-mississippi-missouri",
            "display_link": "https://weather.com \u203a news \u203a news \u203a 2023-03-31-tornad...",
            "title": "Tornadoes, Storms Slam Arkansas, Illinois, Iowa",
            "description": "... across several states, including Arkansas, Indiana, Illinois and Tennessee. - Articles from The Weather Channel | weather.com.",
            "extensions": [
                {
                    "inline": true,
                    "type": "text",
                    "text": "Apr 1, 2023",
                    "rank": 1
                }
            ],
            "rank": 10,
            "global_rank": 10
        }
    ]
}
